setup.cfg
setup.py
coa/__init__.py
coa/coa.py
coa.egg-info/PKG-INFO
coa.egg-info/SOURCES.txt
coa.egg-info/dependency_links.txt
coa.egg-info/requires.txt
coa.egg-info/top_level.txt