Metadata-Version: 1.0
Name: coa
Version: 0.1
Summary: Cuckoo Optimization Algorithm in Python
Home-page: https://github.com/alirezaafzalaghaei/coa
Author: Alireza Afzal aghaei
Author-email: alirezaafzalaghaei@gmail.com
License: LGPLv3
Platform: UNKNOWN
